LICENSE.txt
README.md
setup.cfg
setup.py
sdc_helpers/__init__.py
sdc_helpers/athena_helper.py
sdc_helpers/decorators.py
sdc_helpers/event_bus_helper.py
sdc_helpers/query_helper.py
sdc_helpers/redis_helper.py
sdc_helpers/slack_helper.py
sdc_helpers/utils.py
sdc_helpers.egg-info/PKG-INFO
sdc_helpers.egg-info/SOURCES.txt
sdc_helpers.egg-info/dependency_links.txt
sdc_helpers.egg-info/requires.txt
sdc_helpers.egg-info/top_level.txt
sdc_helpers/airflow_helpers/__init__.py
sdc_helpers/airflow_helpers/dag_factory.py
sdc_helpers/models/__init__.py
sdc_helpers/models/audit.py
sdc_helpers/models/client.py
sdc_helpers/models/model.py
sdc_helpers/models/process.py
sdc_helpers/models/service.py
sdc_helpers/models/subscription.py
sdc_helpers/yaml_helpers/__init__.py
sdc_helpers/yaml_helpers/loaders.py