Metadata-Version: 2.1
Name: sdc-helpers
Version: 1.9.0
Summary: Global SDC Helpers package
Home-page: https://github.com/RingierIMU/sdc-global-all-helpers
Author: Ringier South Africa
Author-email: tools@ringier.co.za
License: UNKNOWN
Download-URL: https://github.com/RingierIMU/sdc-global-all-helpers/archive/v1.9.0.zip
Keywords: pip,helpers
Platform: UNKNOWN
Provides-Extra: airflow
